{
  "project_info": {
    "project_number": "445084760019",
    "firebase_url": "https://catan-master.firebaseio.com",
    "project_id": "catan-master",
    "storage_bucket": "catan-master.appspot.com"
  },
  "client": [
    {
      "client_info": {
        "mobilesdk_app_id": "1:445084760019:android:bca210c7021debecd8a126",
        "android_client_info": {
          "package_name": "tea.white.catan_master"
        }
      },
      "oauth_client": [
        {
          "client_id": "445084760019-9o69lb66lob27j7ov29hb2fmasi2cgg0.apps.googleusercontent.com",
          "client_type": 3
        }
      ],
      "api_key": [
        {
          "current_key": "AIzaSyDiZ2hdMbfZ3kk8goa9zyzmTHNMXJmh5Io"
        }
      ],
      "services": {
        "appinvite_service": {
          "other_platform_oauth_client": [
            {
              "client_id": "445084760019-9o69lb66lob27j7ov29hb2fmasi2cgg0.apps.googleusercontent.com",
              "client_type": 3
            }
          ]
        }
      }
    }
  ],
  "configuration_version": "1"
}